processcontroller/__init__.py
processcontroller-0.1.0.dist-info/LICENSE
processcontroller-0.1.0.dist-info/METADATA
processcontroller-0.1.0.dist-info/WHEEL
processcontroller-0.1.0.dist-info/top_level.txt
processcontroller-0.1.0.dist-info/RECORD
