Metadata-Version: 2.1
Name: processcontroller
Version: 0.1.0
Summary: Replacement for pexpect
Home-page: https://github.com/thommignot/processcontroller
Author: Thomas Mignot
Author-email: tmig@yourlabs.org
License: MIT
Keywords: pexpect subprocess
Platform: UNKNOWN
Requires-Python: >=3
